[
    {
        "tipo": "saldo_baixo",
        "condicao": "saldo_atual < 200",
        "mensagem": "Seu saldo está baixo. Tente reduzir seus gastos nos próximos dias."
    },
    {
        "tipo": "gasto_alimentacao_alto",
        "condicao": "gasto_categoria['Alimentação'] < 400",
        "mensagem": "Você está gastando bastante com alimentação este mês."
    },
    {
        "tipo": "muitos_gastos_transporte",
        "condicao": "gasto_categoria['Transporte'] > 250",
        "mensagem": "Seus gastos com transporte estão acima do esperado."
    }
]
